zeph1rr_kuznechik/__init__.py
zeph1rr_kuznechik/__main__.py
zeph1rr_kuznechik/Kuznechik.py
zeph1rr_kuznechik-0.1.0.dist-info/METADATA
zeph1rr_kuznechik-0.1.0.dist-info/WHEEL
zeph1rr_kuznechik-0.1.0.dist-info/RECORD
