Metadata-Version: 2.1
Name: zeph1rr-kuznechik
Version: 0.1.0
Summary: Python package for Kuznechik cryptografy from GOST 34.12
Author: Zeph1rr
Author-email: grianton535@gmail.com
Requires-Python: >=3.11,<4.0
Classifier: Programming Language :: Python :: 3
Classifier: Programming Language :: Python :: 3.11
Requires-Dist: gostcrypto (>=1.2.5,<2.0.0)
